ml_twopointone/__init__.py
ml_twopointone-0.1.0.dist-info/METADATA
ml_twopointone-0.1.0.dist-info/WHEEL
ml_twopointone-0.1.0.dist-info/RECORD
