Metadata-Version: 2.1
Name: ml-twopointone
Version: 0.1.0
Summary: Package including some functions frequently used in machine learning and data science
Author: Eugine Eering, D. Ata
Requires-Python: >=3.11,<4.0
Classifier: Programming Language :: Python :: 3
Classifier: Programming Language :: Python :: 3.11
Requires-Dist: numpy (>=1.25.2,<2.0.0)
